setup.py
bunqclient/__init__.py
bunqclient/bunqdefault.py
bunqclient.egg-info/PKG-INFO
bunqclient.egg-info/SOURCES.txt
bunqclient.egg-info/dependency_links.txt
bunqclient.egg-info/requires.txt
bunqclient.egg-info/top_level.txt