Metadata-Version: 1.1
Name: bunqclient
Version: 2017.7.17
Summary: Python client for the bunq public API
Home-page: https://github.com/bartbroere/bunqclient/
Author: Bart Broere
Author-email: mail@bartbroere.eu
License: MIT
Keywords: bunq,client,bank,api,bunqclient
Platform: UNKNOWN
Classifier: Development Status :: 5 - Production/Stable
Classifier: License :: OSI Approved :: MIT License
Classifier: Programming Language :: Python
Classifier: Programming Language :: Python :: 3
Classifier: Programming Language :: Python :: 3.5
Classifier: Programming Language :: Python :: 3.6
Classifier: Topic :: Office/Business :: Financial
Classifier: Topic :: Utilities
